MANIFEST.in
README.rst
setup.py
azure_elasticluster_current.egg-info/PKG-INFO
azure_elasticluster_current.egg-info/SOURCES.txt
azure_elasticluster_current.egg-info/dependency_links.txt
azure_elasticluster_current.egg-info/entry_points.txt
azure_elasticluster_current.egg-info/pbr.json
azure_elasticluster_current.egg-info/requires.txt
azure_elasticluster_current.egg-info/top_level.txt
docs/Makefile
docs/bash_completion
docs/conf.py
docs/config.template
docs/configure.rst
docs/customize.rst
docs/global.inc
docs/index.rst
docs/install.rst
docs/playbooks.rst
docs/usage.rst
docs/api/elasticluster.rst
docs/api/index.rst
docs/api/makehier.sh
docs/api/elasticluster/cluster.rst
docs/api/elasticluster/conf.rst
docs/api/elasticluster/exceptions.rst
docs/api/elasticluster/gc3_config.rst
docs/api/elasticluster/helpers.rst
docs/api/elasticluster/main.rst
docs/api/elasticluster/module.rst
docs/api/elasticluster/providers.rst
docs/api/elasticluster/repository.rst
docs/api/elasticluster/subcommands.rst
docs/api/elasticluster/providers/ansible_provider.rst
docs/api/elasticluster/providers/ec2_boto.rst
docs/api/elasticluster/providers/gce.rst
docs/api/elasticluster/providers/openstack.rst
docs/html/configure.html
docs/html/customize.html
docs/html/genindex.html
docs/html/index.html
docs/html/install.html
docs/html/objects.inv
docs/html/playbooks.html
docs/html/search.html
docs/html/searchindex.js
docs/html/usage.html
docs/presentations/chosug-20131206/beamerthemegc3.sty
docs/presentations/chosug-20131206/elasticluster.pdf
docs/presentations/chosug-20131206/elasticluster.tex
docs/presentations/chosug-20131206/elasticluster.toc
docs/presentations/chosug-20131206/gc3.sty
docs/presentations/chosug-20131206/uzh_logo_e_pos.pdf
docs/presentations/egiTF2013/beamerthemegc3.sty
docs/presentations/egiTF2013/elasticluster_egi_TF_2013.pdf
docs/presentations/egiTF2013/elasticluster_egi_TF_2013.tex
docs/presentations/egiTF2013/gc3.sty
docs/presentations/egiTF2013/uzh_logo_e_pos.eps
docs/presentations/egiTF2013/uzh_logo_e_pos.pdf
docs/presentations/euroscipy2013/beamerthemegc3.sty
docs/presentations/euroscipy2013/elasticluster_euroscipy_2013.pdf
docs/presentations/euroscipy2013/elasticluster_euroscipy_2013.tex
docs/presentations/euroscipy2013/gc3.sty
elasticluster/__init__.py
elasticluster/cluster.py
elasticluster/conf.py
