Metadata-Version: 1.1
Name: azure-elasticluster-current
Version: 0.1.dev2
Summary: A command line tool to create, manage and setup computing clusters hosted on a public or private cloud infrastructure.
Home-page: https://github.com/gc3-uzh-ch/elasticluster
Author: Grid Computing Competence Centre, University of Zurich
Author-email: info@gc3.lists.uzh.ch
License: LGPL
Keywords: cloud openstack amazon ec2 ssh hpc gridengine torque slurm batch job elastic
Platform: UNKNOWN
Classifier: Development Status :: 4 - Beta
Classifier: Environment :: Console
Classifier: Intended Audience :: Developers
Classifier: Intended Audience :: Science/Research
Classifier: Intended Audience :: System Administrators
Classifier: License :: OSI Approved :: GNU Library or Lesser General Public License (LGPL)
Classifier: License :: DFSG approved
Classifier: Operating System :: MacOS :: MacOS X
Classifier: Operating System :: POSIX :: Linux
Classifier: Operating System :: POSIX :: Other
Classifier: Programming Language :: Python
Classifier: Programming Language :: Python :: 2
Classifier: Programming Language :: Python :: 2.6
Classifier: Programming Language :: Python :: 2.7
Classifier: Topic :: System :: Clustering
Classifier: Topic :: Education
Classifier: Topic :: Scientific/Engineering
Classifier: Topic :: System :: Distributed Computing
